pyytorch_helper/__init__.py
pyytorch_helper/downloader.py
pyytorch_helper/utils.py
pyytorch_helper-0.1.0.dist-info/METADATA
pyytorch_helper-0.1.0.dist-info/WHEEL
pyytorch_helper-0.1.0.dist-info/top_level.txt
pyytorch_helper-0.1.0.dist-info/RECORD
