Metadata-Version: 2.4
Name: pyytorch-helper
Version: 0.1.0
Summary: A small package that downloads an example dataset on demand
Home-page: https://github.com/yourusername/pyytorch-helper
Author: John Doe
Classifier: Programming Language :: Python :: 3
Classifier: License :: OSI Approved :: MIT License
Classifier: Operating System :: OS Independent
Requires-Python: >=3.7
Requires-Dist: requests
Dynamic: author
Dynamic: classifier
Dynamic: description
Dynamic: description-content-type
Dynamic: home-page
Dynamic: requires-dist
Dynamic: requires-python
Dynamic: summary
